vialink
